shici/__init__.py
shici/favorite.txt
shici-1.0.5.dist-info/LICENSE
shici-1.0.5.dist-info/METADATA
shici-1.0.5.dist-info/WHEEL
shici-1.0.5.dist-info/RECORD
